[
  {
    "approved_account": null,
    "asset": {
      "id": 45187988,
      "token_id": "1309004",
      "num_sales": 2,
      "background_color": null,
      "image_url": "https://lh3.googleusercontent.com/E-WaW712lXPt2BKF1wOPvc3ch0LYn7UWGrIKwVMj7RqItAqTr44cB6awANX8C2dO_ZemSU9-d7w-E8KovpgFbgCOXWTQGTg49f0XVuU",
      "image_preview_url": "https://lh3.googleusercontent.com/E-WaW712lXPt2BKF1wOPvc3ch0LYn7UWGrIKwVMj7RqItAqTr44cB6awANX8C2dO_ZemSU9-d7w-E8KovpgFbgCOXWTQGTg49f0XVuU=s250",
      "image_thumbnail_url": "https://lh3.googleusercontent.com/E-WaW712lXPt2BKF1wOPvc3ch0LYn7UWGrIKwVMj7RqItAqTr44cB6awANX8C2dO_ZemSU9-d7w-E8KovpgFbgCOXWTQGTg49f0XVuU=s128",
      "image_original_url": "https://ipfs.io/ipfs/QmTbCWgTRYpGniZdCpt4V8yNnKvYD6pakADoPBMCGFCW8x/asset.jpg",
      "animation_url": null,
      "animation_original_url": null,
      "name": "Ms Page",
      "description": "Bettie Page",
      "external_link": "https://knownorigin.io/0x9e283900715b62f8923b14fc2cb64088e2d5bd5d",
      "asset_contract": {
        "address": "0xabb3738f04dc2ec20f4ae4462c3d069d02ae045b",
        "asset_contract_type": "non-fungible",
        "created_date": "2021-08-25T10:45:22.442150",
        "name": "KnownOriginDigitalAsset",
        "nft_version": "3.0",
        "opensea_version": null,
        "owner": null,
        "schema_name": "ERC721",
        "symbol": "KODA",
        "total_supply": null,
        "description": "Discover rare digital art and collect NFTs. \r\n\r\nSince Apr. 2018.",
        "external_link": "https://knownorigin.io",
        "image_url": "https://lh3.googleusercontent.com/53L422-5QSOKOaWTu3-EWZkymYoyFo6L60AnxPXqz4rNgX1-E162tIljSyVOa3hyVACvJNGdih4lFummnHPx-1Fa=s60",
        "default_to_fiat": false,
        "dev_buyer_fee_basis_points": 0,
        "dev_seller_fee_basis_points": 1250,
        "only_proxied_transfers": false,
        "opensea_buyer_fee_basis_points": 0,
        "opensea_seller_fee_basis_points": 250,
        "buyer_fee_basis_points": 0,
        "seller_fee_basis_points": 1500,
        "payout_address": "0x11b0d9afd49dc36d86dea579d0d11771a4f2f54b"
      },
      "permalink": "https://opensea.io/assets/0xabb3738f04dc2ec20f4ae4462c3d069d02ae045b/1309004",
      "collection": {
        "banner_image_url": "https://lh3.googleusercontent.com/iL9v2veoF3jjRFI8w9GGVNd0cApJ-ydat-Qr9uVbaf4u0YQTLNBngUUMUstsRFWoVXwOXx1B0-QM-US6--pRhEYnp1eulaR8cNbEew=s2500",
        "chat_url": null,
        "created_date": "2019-04-26T22:13:10.262099",
        "default_to_fiat": false,
        "description": "Discover rare digital art and collect NFTs. \r\n\r\nSince Apr. 2018.",
        "dev_buyer_fee_basis_points": "0",
        "dev_seller_fee_basis_points": "1250",
        "discord_url": "https://discord.gg/yqgnNyZ",
        "display_data": {
          "card_display_style": "cover"
        },
        "external_url": "https://knownorigin.io",
        "featured": false,
        "featured_image_url": "https://lh3.googleusercontent.com/C8EnLXgLFLqA_o-7FdUzUGb2U0Q_N-QXjvqwv648G0RJ8smrA6UpYzcvIl6q4a2YaR-r9sbukD2f2IXPgPInywITco_eQq3d5B_smw=s300",
        "hidden": false,
        "safelist_request_status": "verified",
        "image_url": "https://lh3.googleusercontent.com/53L422-5QSOKOaWTu3-EWZkymYoyFo6L60AnxPXqz4rNgX1-E162tIljSyVOa3hyVACvJNGdih4lFummnHPx-1Fa=s60",
        "is_subject_to_whitelist": false,
        "large_image_url": "https://lh3.googleusercontent.com/C8EnLXgLFLqA_o-7FdUzUGb2U0Q_N-QXjvqwv648G0RJ8smrA6UpYzcvIl6q4a2YaR-r9sbukD2f2IXPgPInywITco_eQq3d5B_smw=s300",
        "medium_username": "knownorigin",
        "name": "KnownOrigin",
        "only_proxied_transfers": false,
        "opensea_buyer_fee_basis_points": "0",
        "opensea_seller_fee_basis_points": "250",
        "payout_address": "0x11b0d9afd49dc36d86dea579d0d11771a4f2f54b",
        "require_email": false,
        "short_description": null,
        "slug": "known-origin",
        "telegram_url": "https://t.me/knownorigin_io",
        "twitter_username": "knownorigin_io",
        "instagram_username": "knownorigin.io",
        "wiki_url": null
      },
      "decimals": 0,
      "token_metadata": "https://ipfs.io/ipfs/Qmd59XxUnReCkibGxt9KrGymVA6m5okX4jgJTRSTUbub4T",
      "owner": {
        "user": null,
        "profile_img_url": "https://storage.googleapis.com/opensea-static/opensea-profile/2.png",
        "address": "0x7241794fd24e70566a401b296b9e05d761691cd9",
        "config": ""
      }
    },
    "asset_bundle": null,
    "auction_type": null,
    "bid_amount": null,
    "collection_slug": "known-origin",
    "contract_address": "0x7be8076f4ea4a4ad08075c2508e481d6c946d12b",
    "created_date": "2021-12-21T08:45:48.914758",
    "custom_event_name": null,
    "dev_fee_payment_event": {
      "asset": null,
      "asset_bundle": null,
      "event_type": "payout",
      "event_timestamp": "2021-12-25T21:05:30",
      "auction_type": null,
      "total_price": null,
      "payment_token": {
        "id": 1,
        "symbol": "ETH",
        "address": "0x0000000000000000000000000000000000000000",
        "image_url": "https://storage.opensea.io/files/6f8e2979d428180222796ff4a33ab929.svg",
        "name": "Ether",
        "decimals": 18,
        "eth_price": "1.000000000000000",
        "usd_price": "3139.480000000000018000"
      },
      "transaction": {
        "block_hash": "0x867724c9a6a66bbfbfcc6bdb55e894f3c3a65eb8821424413ca785184b8cf7cd",
        "block_number": "13876671",
        "from_account": null,
        "id": 232155976,
        "timestamp": null,
        "to_account": null,
        "transaction_hash": "0xdd4dec52cf1ee2b8283db7c49376814fe0c6ecbb8df88ca73f14f7328d41815d",
        "transaction_index": "43"
      },
      "created_date": "2021-12-25T21:05:47.802312",
      "quantity": null
    },
    "dev_seller_fee_basis_points": 1250,
    "duration": null,
    "ending_price": null,
    "event_type": "successful",
    "from_account": null,
    "id": 2569229631,
    "is_private": true,
    "owner_account": null,
    "payment_token": {
      "id": 1,
      "symbol": "ETH",
      "address": "0x0000000000000000000000000000000000000000",
      "image_url": "https://storage.opensea.io/files/6f8e2979d428180222796ff4a33ab929.svg",
      "name": "Ether",
      "decimals": 18,
      "eth_price": "1.000000000000000",
      "usd_price": "3139.480000000000018000"
    },
    "quantity": "1",
    "seller": {
      "user": {
        "username": "rofnebidd"
      },
      "profile_img_url": "https://storage.googleapis.com/opensea-static/opensea-profile/2.png",
      "address": "0x8cf85548ae57a91f8132d0831634c0fcef06e505",
      "config": ""
    },
    "starting_price": null,
    "to_account": null,
    "total_price": "1000000000000000",
    "transaction": {
      "block_hash": "0xb0068b880ad72d4b40a2f88d4d9124f28a5dbe8be29ee4496e4c29e957e42ee5",
      "block_number": "13847536",
      "from_account": {
        "user": null,
        "profile_img_url": "https://storage.googleapis.com/opensea-static/opensea-profile/2.png",
        "address": "0x7241794fd24e70566a401b296b9e05d761691cd9",
        "config": ""
      },
      "id": 228445499,
      "timestamp": "2021-12-21T08:45:30",
      "to_account": {
        "user": {
          "username": "OpenSea-Orders"
        },
        "profile_img_url": "https://storage.googleapis.com/opensea-static/opensea-profile/22.png",
        "address": "0x7be8076f4ea4a4ad08075c2508e481d6c946d12b",
        "config": "verified"
      },
      "transaction_hash": "0xa69c978853593d5fa436f2d5faec4a51156e07dc0e6c4bef3405d553e25adcfc",
      "transaction_index": "106"
    },
    "winner_account": {
      "user": null,
      "profile_img_url": "https://storage.googleapis.com/opensea-static/opensea-profile/2.png",
      "address": "0x7241794fd24e70566a401b296b9e05d761691cd9",
      "config": ""
    },
    "listing_time": "2021-12-20T00:26:30"
  },
  {
    "approved_account": null,
    "asset": {
      "id": 51130198,
      "token_id": "1712016",
      "num_sales": 1,
      "background_color": null,
      "image_url": "https://lh3.googleusercontent.com/il6-YOc5Yg0Uxm73AgqCeuDfDVL_4JTwcHgm-tOOTA1W1xMcovRTuyrAgTbo8rFjLsq9Oz1opLPH6BZoJOVCx38uS3y2G3gLexwf",
      "image_preview_url": "https://lh3.googleusercontent.com/il6-YOc5Yg0Uxm73AgqCeuDfDVL_4JTwcHgm-tOOTA1W1xMcovRTuyrAgTbo8rFjLsq9Oz1opLPH6BZoJOVCx38uS3y2G3gLexwf=s250",
      "image_thumbnail_url": "https://lh3.googleusercontent.com/il6-YOc5Yg0Uxm73AgqCeuDfDVL_4JTwcHgm-tOOTA1W1xMcovRTuyrAgTbo8rFjLsq9Oz1opLPH6BZoJOVCx38uS3y2G3gLexwf=s128",
      "image_original_url": "https://ipfs.io/ipfs/QmRGLHCQFEN9HHLkKgRmssFqA5pjsEXsqPa3hX29wg8jvE/asset.jpg",
      "animation_url": null,
      "animation_original_url": null,
      "name": "Bettie II",
      "description": "Digital art of Bettie Page",
      "external_link": "https://knownorigin.io/0x9e283900715b62f8923b14fc2cb64088e2d5bd5d",
      "asset_contract": {
        "address": "0xabb3738f04dc2ec20f4ae4462c3d069d02ae045b",
        "asset_contract_type": "non-fungible",
        "created_date": "2021-08-25T10:45:22.442150",
        "name": "KnownOriginDigitalAsset",
        "nft_version": "3.0",
        "opensea_version": null,
        "owner": null,
        "schema_name": "ERC721",
        "symbol": "KODA",
        "total_supply": null,
        "description": "Discover rare digital art and collect NFTs. \r\n\r\nSince Apr. 2018.",
        "external_link": "https://knownorigin.io",
        "image_url": "https://lh3.googleusercontent.com/53L422-5QSOKOaWTu3-EWZkymYoyFo6L60AnxPXqz4rNgX1-E162tIljSyVOa3hyVACvJNGdih4lFummnHPx-1Fa=s60",
        "default_to_fiat": false,
        "dev_buyer_fee_basis_points": 0,
        "dev_seller_fee_basis_points": 1250,
        "only_proxied_transfers": false,
        "opensea_buyer_fee_basis_points": 0,
        "opensea_seller_fee_basis_points": 250,
        "buyer_fee_basis_points": 0,
        "seller_fee_basis_points": 1500,
        "payout_address": "0x11b0d9afd49dc36d86dea579d0d11771a4f2f54b"
      },
      "permalink": "https://opensea.io/assets/0xabb3738f04dc2ec20f4ae4462c3d069d02ae045b/1712016",
      "collection": {
        "banner_image_url": "https://lh3.googleusercontent.com/iL9v2veoF3jjRFI8w9GGVNd0cApJ-ydat-Qr9uVbaf4u0YQTLNBngUUMUstsRFWoVXwOXx1B0-QM-US6--pRhEYnp1eulaR8cNbEew=s2500",
        "chat_url": null,
        "created_date": "2019-04-26T22:13:10.262099",
        "default_to_fiat": false,
        "description": "Discover rare digital art and collect NFTs. \r\n\r\nSince Apr. 2018.",
        "dev_buyer_fee_basis_points": "0",
        "dev_seller_fee_basis_points": "1250",
        "discord_url": "https://discord.gg/yqgnNyZ",
        "display_data": {
          "card_display_style": "cover"
        },
        "external_url": "https://knownorigin.io",
        "featured": false,
        "featured_image_url": "https://lh3.googleusercontent.com/C8EnLXgLFLqA_o-7FdUzUGb2U0Q_N-QXjvqwv648G0RJ8smrA6UpYzcvIl6q4a2YaR-r9sbukD2f2IXPgPInywITco_eQq3d5B_smw=s300",
        "hidden": false,
        "safelist_request_status": "verified",
        "image_url": "https://lh3.googleusercontent.com/53L422-5QSOKOaWTu3-EWZkymYoyFo6L60AnxPXqz4rNgX1-E162tIljSyVOa3hyVACvJNGdih4lFummnHPx-1Fa=s60",
        "is_subject_to_whitelist": false,
        "large_image_url": "https://lh3.googleusercontent.com/C8EnLXgLFLqA_o-7FdUzUGb2U0Q_N-QXjvqwv648G0RJ8smrA6UpYzcvIl6q4a2YaR-r9sbukD2f2IXPgPInywITco_eQq3d5B_smw=s300",
        "medium_username": "knownorigin",
        "name": "KnownOrigin",
        "only_proxied_transfers": false,
        "opensea_buyer_fee_basis_points": "0",
        "opensea_seller_fee_basis_points": "250",
        "payout_address": "0x11b0d9afd49dc36d86dea579d0d11771a4f2f54b",
        "require_email": false,
        "short_description": null,
        "slug": "known-origin",
        "telegram_url": "https://t.me/knownorigin_io",
        "twitter_username": "knownorigin_io",
        "instagram_username": "knownorigin.io",
        "wiki_url": null
      },
      "decimals": 0,
      "token_metadata": "https://ipfs.io/ipfs/Qmbh5SPMjbk2gcrbURjCkCFZCjpQ3NzabnRcT7ST4YWtZM",
      "owner": {
        "user": null,
        "profile_img_url": "https://storage.googleapis.com/opensea-static/opensea-profile/2.png",
        "address": "0x7241794fd24e70566a401b296b9e05d761691cd9",
        "config": ""
      }
    },
    "asset_bundle": null,
    "auction_type": null,
    "bid_amount": null,
    "collection_slug": "known-origin",
    "contract_address": "0x7be8076f4ea4a4ad08075c2508e481d6c946d12b",
    "created_date": "2021-12-21T08:45:49.183398",
    "custom_event_name": null,
    "dev_fee_payment_event": {
      "asset": null,
      "asset_bundle": null,
      "event_type": "payout",
      "event_timestamp": "2021-12-25T21:05:30",
      "auction_type": null,
      "total_price": null,
      "payment_token": {
        "id": 1,
        "symbol": "ETH",
        "address": "0x0000000000000000000000000000000000000000",
        "image_url": "https://storage.opensea.io/files/6f8e2979d428180222796ff4a33ab929.svg",
        "name": "Ether",
        "decimals": 18,
        "eth_price": "1.000000000000000",
        "usd_price": "3139.480000000000018000"
      },
      "transaction": {
        "block_hash": "0x867724c9a6a66bbfbfcc6bdb55e894f3c3a65eb8821424413ca785184b8cf7cd",
        "block_number": "13876671",
        "from_account": null,
        "id": 232155976,
        "timestamp": null,
        "to_account": null,
        "transaction_hash": "0xdd4dec52cf1ee2b8283db7c49376814fe0c6ecbb8df88ca73f14f7328d41815d",
        "transaction_index": "43"
      },
      "created_date": "2021-12-25T21:05:47.802312",
      "quantity": null
    },
    "dev_seller_fee_basis_points": 1250,
    "duration": null,
    "ending_price": null,
    "event_type": "successful",
    "from_account": null,
    "id": 2569229657,
    "is_private": true,
    "owner_account": null,
    "payment_token": {
      "id": 1,
      "symbol": "ETH",
      "address": "0x0000000000000000000000000000000000000000",
      "image_url": "https://storage.opensea.io/files/6f8e2979d428180222796ff4a33ab929.svg",
      "name": "Ether",
      "decimals": 18,
      "eth_price": "1.000000000000000",
      "usd_price": "3139.480000000000018000"
    },
    "quantity": "1",
    "seller": {
      "user": {
        "username": "rofnebidd"
      },
      "profile_img_url": "https://storage.googleapis.com/opensea-static/opensea-profile/2.png",
      "address": "0x8cf85548ae57a91f8132d0831634c0fcef06e505",
      "config": ""
    },
    "starting_price": null,
    "to_account": null,
    "total_price": "1000000000000000",
    "transaction": {
      "block_hash": "0xb0068b880ad72d4b40a2f88d4d9124f28a5dbe8be29ee4496e4c29e957e42ee5",
      "block_number": "13847536",
      "from_account": {
        "user": null,
        "profile_img_url": "https://storage.googleapis.com/opensea-static/opensea-profile/2.png",
        "address": "0x7241794fd24e70566a401b296b9e05d761691cd9",
        "config": ""
      },
      "id": 228445504,
      "timestamp": "2021-12-21T08:45:30",
      "to_account": {
        "user": {
          "username": "OpenSea-Orders"
        },
        "profile_img_url": "https://storage.googleapis.com/opensea-static/opensea-profile/22.png",
        "address": "0x7be8076f4ea4a4ad08075c2508e481d6c946d12b",
        "config": "verified"
      },
      "transaction_hash": "0xf27c4060f4318a30c72d3fb217adf94149058b24e6d96949fffc368359d3ede7",
      "transaction_index": "105"
    },
    "winner_account": {
      "user": null,
      "profile_img_url": "https://storage.googleapis.com/opensea-static/opensea-profile/2.png",
      "address": "0x7241794fd24e70566a401b296b9e05d761691cd9",
      "config": ""
    },
    "listing_time": "2021-12-20T00:19:56"
  },
  {
    "approved_account": null,
    "asset": {
      "id": 51130203,
      "token_id": "1712017",
      "num_sales": 1,
      "background_color": null,
      "image_url": "https://lh3.googleusercontent.com/il6-YOc5Yg0Uxm73AgqCeuDfDVL_4JTwcHgm-tOOTA1W1xMcovRTuyrAgTbo8rFjLsq9Oz1opLPH6BZoJOVCx38uS3y2G3gLexwf",
      "image_preview_url": "https://lh3.googleusercontent.com/il6-YOc5Yg0Uxm73AgqCeuDfDVL_4JTwcHgm-tOOTA1W1xMcovRTuyrAgTbo8rFjLsq9Oz1opLPH6BZoJOVCx38uS3y2G3gLexwf=s250",
      "image_thumbnail_url": "https://lh3.googleusercontent.com/il6-YOc5Yg0Uxm73AgqCeuDfDVL_4JTwcHgm-tOOTA1W1xMcovRTuyrAgTbo8rFjLsq9Oz1opLPH6BZoJOVCx38uS3y2G3gLexwf=s128",
      "image_original_url": "https://ipfs.io/ipfs/QmRGLHCQFEN9HHLkKgRmssFqA5pjsEXsqPa3hX29wg8jvE/asset.jpg",
      "animation_url": null,
      "animation_original_url": null,
      "name": "Bettie II",
      "description": "Digital art of Bettie Page",
      "external_link": "https://knownorigin.io/0x9e283900715b62f8923b14fc2cb64088e2d5bd5d",
      "asset_contract": {
        "address": "0xabb3738f04dc2ec20f4ae4462c3d069d02ae045b",
        "asset_contract_type": "non-fungible",
        "created_date": "2021-08-25T10:45:22.442150",
        "name": "KnownOriginDigitalAsset",
        "nft_version": "3.0",
        "opensea_version": null,
        "owner": null,
        "schema_name": "ERC721",
        "symbol": "KODA",
        "total_supply": null,
        "description": "Discover rare digital art and collect NFTs. \r\n\r\nSince Apr. 2018.",
        "external_link": "https://knownorigin.io",
        "image_url": "https://lh3.googleusercontent.com/53L422-5QSOKOaWTu3-EWZkymYoyFo6L60AnxPXqz4rNgX1-E162tIljSyVOa3hyVACvJNGdih4lFummnHPx-1Fa=s60",
        "default_to_fiat": false,
        "dev_buyer_fee_basis_points": 0,
        "dev_seller_fee_basis_points": 1250,
        "only_proxied_transfers": false,
        "opensea_buyer_fee_basis_points": 0,
        "opensea_seller_fee_basis_points": 250,
        "buyer_fee_basis_points": 0,
        "seller_fee_basis_points": 1500,
        "payout_address": "0x11b0d9afd49dc36d86dea579d0d11771a4f2f54b"
      },
      "permalink": "https://opensea.io/assets/0xabb3738f04dc2ec20f4ae4462c3d069d02ae045b/1712017",
      "collection": {
        "banner_image_url": "https://lh3.googleusercontent.com/iL9v2veoF3jjRFI8w9GGVNd0cApJ-ydat-Qr9uVbaf4u0YQTLNBngUUMUstsRFWoVXwOXx1B0-QM-US6--pRhEYnp1eulaR8cNbEew=s2500",
        "chat_url": null,
        "created_date": "2019-04-26T22:13:10.262099",
        "default_to_fiat": false,
        "description": "Discover rare digital art and collect NFTs. \r\n\r\nSince Apr. 2018.",
        "dev_buyer_fee_basis_points": "0",
        "dev_seller_fee_basis_points": "1250",
        "discord_url": "https://discord.gg/yqgnNyZ",
        "display_data": {
          "card_display_style": "cover"
        },
        "external_url": "https://knownorigin.io",
        "featured": false,
        "featured_image_url": "https://lh3.googleusercontent.com/C8EnLXgLFLqA_o-7FdUzUGb2U0Q_N-QXjvqwv648G0RJ8smrA6UpYzcvIl6q4a2YaR-r9sbukD2f2IXPgPInywITco_eQq3d5B_smw=s300",
        "hidden": false,
        "safelist_request_status": "verified",
        "image_url": "https://lh3.googleusercontent.com/53L422-5QSOKOaWTu3-EWZkymYoyFo6L60AnxPXqz4rNgX1-E162tIljSyVOa3hyVACvJNGdih4lFummnHPx-1Fa=s60",
        "is_subject_to_whitelist": false,
        "large_image_url": "https://lh3.googleusercontent.com/C8EnLXgLFLqA_o-7FdUzUGb2U0Q_N-QXjvqwv648G0RJ8smrA6UpYzcvIl6q4a2YaR-r9sbukD2f2IXPgPInywITco_eQq3d5B_smw=s300",
        "medium_username": "knownorigin",
        "name": "KnownOrigin",
        "only_proxied_transfers": false,
        "opensea_buyer_fee_basis_points": "0",
        "opensea_seller_fee_basis_points": "250",
        "payout_address": "0x11b0d9afd49dc36d86dea579d0d11771a4f2f54b",
        "require_email": false,
        "short_description": null,
        "slug": "known-origin",
        "telegram_url": "https://t.me/knownorigin_io",
        "twitter_username": "knownorigin_io",
        "instagram_username": "knownorigin.io",
        "wiki_url": null
      },
      "decimals": 0,
      "token_metadata": "https://ipfs.io/ipfs/Qmbh5SPMjbk2gcrbURjCkCFZCjpQ3NzabnRcT7ST4YWtZM",
      "owner": {
        "user": null,
        "profile_img_url": "https://storage.googleapis.com/opensea-static/opensea-profile/2.png",
        "address": "0x7241794fd24e70566a401b296b9e05d761691cd9",
        "config": ""
      }
    },
    "asset_bundle": null,
    "auction_type": null,
    "bid_amount": null,
    "collection_slug": "known-origin",
    "contract_address": "0x7be8076f4ea4a4ad08075c2508e481d6c946d12b",
    "created_date": "2021-12-21T08:45:47.970032",
    "custom_event_name": null,
    "dev_fee_payment_event": {
      "asset": null,
      "asset_bundle": null,
      "event_type": "payout",
      "event_timestamp": "2021-12-25T21:05:30",
      "auction_type": null,
      "total_price": null,
      "payment_token": {
        "id": 1,
        "symbol": "ETH",
        "address": "0x0000000000000000000000000000000000000000",
        "image_url": "https://storage.opensea.io/files/6f8e2979d428180222796ff4a33ab929.svg",
        "name": "Ether",
        "decimals": 18,
        "eth_price": "1.000000000000000",
        "usd_price": "3139.480000000000018000"
      },
      "transaction": {
        "block_hash": "0x867724c9a6a66bbfbfcc6bdb55e894f3c3a65eb8821424413ca785184b8cf7cd",
        "block_number": "13876671",
        "from_account": null,
        "id": 232155976,
        "timestamp": null,
        "to_account": null,
        "transaction_hash": "0xdd4dec52cf1ee2b8283db7c49376814fe0c6ecbb8df88ca73f14f7328d41815d",
        "transaction_index": "43"
      },
      "created_date": "2021-12-25T21:05:47.802312",
      "quantity": null
    },
    "dev_seller_fee_basis_points": 1250,
    "duration": null,
    "ending_price": null,
    "event_type": "successful",
    "from_account": null,
    "id": 2569229560,
    "is_private": true,
    "owner_account": null,
    "payment_token": {
      "id": 1,
      "symbol": "ETH",
      "address": "0x0000000000000000000000000000000000000000",
      "image_url": "https://storage.opensea.io/files/6f8e2979d428180222796ff4a33ab929.svg",
      "name": "Ether",
      "decimals": 18,
      "eth_price": "1.000000000000000",
      "usd_price": "3139.480000000000018000"
    },
    "quantity": "1",
    "seller": {
      "user": {
        "username": "rofnebidd"
      },
      "profile_img_url": "https://storage.googleapis.com/opensea-static/opensea-profile/2.png",
      "address": "0x8cf85548ae57a91f8132d0831634c0fcef06e505",
      "config": ""
    },
    "starting_price": null,
    "to_account": null,
    "total_price": "1000000000000000",
    "transaction": {
      "block_hash": "0x6016f5dd080356d2b97310dc27a64f6beb2b11f7d17d2906f8366b9b09248a34",
      "block_number": "13847535",
      "from_account": {
        "user": null,
        "profile_img_url": "https://storage.googleapis.com/opensea-static/opensea-profile/2.png",
        "address": "0x7241794fd24e70566a401b296b9e05d761691cd9",
        "config": ""
      },
      "id": 228445469,
      "timestamp": "2021-12-21T08:45:29",
      "to_account": {
        "user": {
          "username": "OpenSea-Orders"
        },
        "profile_img_url": "https://storage.googleapis.com/opensea-static/opensea-profile/22.png",
        "address": "0x7be8076f4ea4a4ad08075c2508e481d6c946d12b",
        "config": "verified"
      },
      "transaction_hash": "0xc85afede830c6afde80efb372d6f3a962d1f843892aa5e8bc47aaaaff9e0d610",
      "transaction_index": "90"
    },
    "winner_account": {
      "user": null,
      "profile_img_url": "https://storage.googleapis.com/opensea-static/opensea-profile/2.png",
      "address": "0x7241794fd24e70566a401b296b9e05d761691cd9",
      "config": ""
    },
    "listing_time": "2021-12-20T00:18:59"
  },
  {
    "approved_account": null,
    "asset": {
      "id": 33196294,
      "token_id": "576302",
      "num_sales": 2,
      "background_color": null,
      "image_url": "https://lh3.googleusercontent.com/vgSc8qIq0cEmWfkNjHusom8HdlAX6m6-S9f1r34xrX1iD0lqjzY7oYU7o3x2vV-pbqa5M7P_UpXncw0S_YmTqGPqjNeVm80RBk388A",
      "image_preview_url": "https://lh3.googleusercontent.com/vgSc8qIq0cEmWfkNjHusom8HdlAX6m6-S9f1r34xrX1iD0lqjzY7oYU7o3x2vV-pbqa5M7P_UpXncw0S_YmTqGPqjNeVm80RBk388A=s250",
      "image_thumbnail_url": "https://lh3.googleusercontent.com/vgSc8qIq0cEmWfkNjHusom8HdlAX6m6-S9f1r34xrX1iD0lqjzY7oYU7o3x2vV-pbqa5M7P_UpXncw0S_YmTqGPqjNeVm80RBk388A=s128",
      "image_original_url": "https://ipfs.infura.io/ipfs/QmdfxXxWTupWTCEhm1BZLoUBdDJzmEgGE2minBQhD9rCB1/asset.jpeg",
      "animation_url": null,
      "animation_original_url": null,
      "name": "Future Rock 2021 Sabet",
      "description": "Time is an illusion. Connect. Be present. This is it. Enjoy yourself. The future is now.",
      "external_link": "https://knownorigin.io/token/576302",
      "asset_contract": {
        "address": "0xfbeef911dc5821886e1dda71586d90ed28174b7d",
        "asset_contract_type": "non-fungible",
        "created_date": "2018-09-26T14:13:07.725021",
        "name": "Known Origin",
        "nft_version": "3.0",
        "opensea_version": null,
        "owner": 82615,
        "schema_name": "ERC721",
        "symbol": "KODA",
        "total_supply": null,
        "description": "Discover rare digital art and collect NFTs. \r\n\r\nSince Apr. 2018.",
        "external_link": "https://knownorigin.io",
        "image_url": "https://lh3.googleusercontent.com/53L422-5QSOKOaWTu3-EWZkymYoyFo6L60AnxPXqz4rNgX1-E162tIljSyVOa3hyVACvJNGdih4lFummnHPx-1Fa=s60",
        "default_to_fiat": false,
        "dev_buyer_fee_basis_points": 0,
        "dev_seller_fee_basis_points": 1250,
        "only_proxied_transfers": false,
        "opensea_buyer_fee_basis_points": 0,
        "opensea_seller_fee_basis_points": 250,
        "buyer_fee_basis_points": 0,
        "seller_fee_basis_points": 1500,
        "payout_address": "0x11b0d9afd49dc36d86dea579d0d11771a4f2f54b"
      },
      "permalink": "https://opensea.io/assets/0xfbeef911dc5821886e1dda71586d90ed28174b7d/576302",
      "collection": {
        "banner_image_url": "https://lh3.googleusercontent.com/iL9v2veoF3jjRFI8w9GGVNd0cApJ-ydat-Qr9uVbaf4u0YQTLNBngUUMUstsRFWoVXwOXx1B0-QM-US6--pRhEYnp1eulaR8cNbEew=s2500",
        "chat_url": null,
        "created_date": "2019-04-26T22:13:10.262099",
        "default_to_fiat": false,
        "description": "Discover rare digital art and collect NFTs. \r\n\r\nSince Apr. 2018.",
        "dev_buyer_fee_basis_points": "0",
        "dev_seller_fee_basis_points": "1250",
        "discord_url": "https://discord.gg/yqgnNyZ",
        "display_data": {
          "card_display_style": "cover"
        },
        "external_url": "https://knownorigin.io",
        "featured": false,
        "featured_image_url": "https://lh3.googleusercontent.com/C8EnLXgLFLqA_o-7FdUzUGb2U0Q_N-QXjvqwv648G0RJ8smrA6UpYzcvIl6q4a2YaR-r9sbukD2f2IXPgPInywITco_eQq3d5B_smw=s300",
        "hidden": false,
        "safelist_request_status": "verified",
        "image_url": "https://lh3.googleusercontent.com/53L422-5QSOKOaWTu3-EWZkymYoyFo6L60AnxPXqz4rNgX1-E162tIljSyVOa3hyVACvJNGdih4lFummnHPx-1Fa=s60",
        "is_subject_to_whitelist": false,
        "large_image_url": "https://lh3.googleusercontent.com/C8EnLXgLFLqA_o-7FdUzUGb2U0Q_N-QXjvqwv648G0RJ8smrA6UpYzcvIl6q4a2YaR-r9sbukD2f2IXPgPInywITco_eQq3d5B_smw=s300",
        "medium_username": "knownorigin",
        "name": "KnownOrigin",
        "only_proxied_transfers": false,
        "opensea_buyer_fee_basis_points": "0",
        "opensea_seller_fee_basis_points": "250",
        "payout_address": "0x11b0d9afd49dc36d86dea579d0d11771a4f2f54b",
        "require_email": false,
        "short_description": null,
        "slug": "known-origin",
        "telegram_url": "https://t.me/knownorigin_io",
        "twitter_username": "knownorigin_io",
        "instagram_username": "knownorigin.io",
        "wiki_url": null
      },
      "decimals": 0,
      "token_metadata": "https://ipfs.infura.io/ipfs/QmTpfGNUK4E9S8K91Ky3ujuoSw9j3FGZ2fa9c6478VP3Eb",
      "owner": {
        "user": {
          "username": "Jimsvault"
        },
        "profile_img_url": "https://storage.googleapis.com/opensea-static/opensea-profile/6.png",
        "address": "0x010acffec14a6413b3efaab0023996559edc4878",
        "config": ""
      }
    },
    "asset_bundle": null,
    "auction_type": null,
    "bid_amount": null,
    "collection_slug": "known-origin",
    "contract_address": "0x7be8076f4ea4a4ad08075c2508e481d6c946d12b",
    "created_date": "2021-12-30T05:45:25.825958",
    "custom_event_name": null,
    "dev_fee_payment_event": {
      "asset": null,
      "asset_bundle": null,
      "event_type": "payout",
      "event_timestamp": "2022-01-04T14:17:17",
      "auction_type": null,
      "total_price": null,
      "payment_token": {
        "id": 1,
        "symbol": "ETH",
        "address": "0x0000000000000000000000000000000000000000",
        "image_url": "https://storage.opensea.io/files/6f8e2979d428180222796ff4a33ab929.svg",
        "name": "Ether",
        "decimals": 18,
        "eth_price": "1.000000000000000",
        "usd_price": "3139.480000000000018000"
      },
      "transaction": {
        "block_hash": "0xce14ca0c1a36c0f55e79e8ace249bd98ca5ec4f05e7266cc9373e4ddd34ee13b",
        "block_number": "13939459",
        "from_account": null,
        "id": 240226195,
        "timestamp": null,
        "to_account": null,
        "transaction_hash": "0x39e4c11a02bc39cbb440acd1d47a76b63af630fc78647a68ca07105eb777cb2f",
        "transaction_index": "103"
      },
      "created_date": "2022-01-04T14:17:41.083176",
      "quantity": null
    },
    "dev_seller_fee_basis_points": 1250,
    "duration": null,
    "ending_price": null,
    "event_type": "successful",
    "from_account": null,
    "id": 2668624364,
    "is_private": true,
    "owner_account": null,
    "payment_token": {
      "id": 1,
      "symbol": "ETH",
      "address": "0x0000000000000000000000000000000000000000",
      "image_url": "https://storage.opensea.io/files/6f8e2979d428180222796ff4a33ab929.svg",
      "name": "Ether",
      "decimals": 18,
      "eth_price": "1.000000000000000",
      "usd_price": "3139.480000000000018000"
    },
    "quantity": "1",
    "seller": {
      "user": {
        "username": "0xStealth"
      },
      "profile_img_url": "https://storage.googleapis.com/opensea-static/opensea-profile/20.png",
      "address": "0x4ecd82114f73c9f2debab6f08c9891fc742ad472",
      "config": ""
    },
    "starting_price": null,
    "to_account": null,
    "total_price": "180000000000000000",
    "transaction": {
      "block_hash": "0x456d661a82f5c27e1e3117b583d48848b2c46d2651406368642533adba0b4630",
      "block_number": "13904908",
      "from_account": {
        "user": {
          "username": "carys"
        },
        "profile_img_url": "https://storage.googleapis.com/opensea-static/opensea-profile/31.png",
        "address": "0xd711e8975f248216dba4730c06fc86b9aa765f92",
        "config": ""
      },
      "id": 235754980,
      "timestamp": "2021-12-30T05:45:08",
      "to_account": {
        "user": {
          "username": "OpenSea-Orders"
        },
        "profile_img_url": "https://storage.googleapis.com/opensea-static/opensea-profile/22.png",
        "address": "0x7be8076f4ea4a4ad08075c2508e481d6c946d12b",
        "config": "verified"
      },
      "transaction_hash": "0x059113e4c0ac7476aafdea3c8e2aa8b52c63e36017091e22b365fa04bb1b5ca8",
      "transaction_index": "47"
    },
    "winner_account": {
      "user": {
        "username": "carys"
      },
      "profile_img_url": "https://storage.googleapis.com/opensea-static/opensea-profile/31.png",
      "address": "0xd711e8975f248216dba4730c06fc86b9aa765f92",
      "config": ""
    },
    "listing_time": "2021-12-29T20:29:54"
  },
  {
    "approved_account": null,
    "asset": {
      "id": 35384138,
      "token_id": "611423",
      "num_sales": 2,
      "background_color": null,
      "image_url": "https://lh3.googleusercontent.com/tQsgEhRfHr9cgEk3Mna-yOTUlrQsaxi2TWsFpW6OkQQUiY0z-TFkD88IeD8aTJ2Lr_pYQ07XCXTWXUBN4q2TCMG-sJ9gmXfRBhfk",
      "image_preview_url": "https://lh3.googleusercontent.com/tQsgEhRfHr9cgEk3Mna-yOTUlrQsaxi2TWsFpW6OkQQUiY0z-TFkD88IeD8aTJ2Lr_pYQ07XCXTWXUBN4q2TCMG-sJ9gmXfRBhfk=s250",
      "image_thumbnail_url": "https://lh3.googleusercontent.com/tQsgEhRfHr9cgEk3Mna-yOTUlrQsaxi2TWsFpW6OkQQUiY0z-TFkD88IeD8aTJ2Lr_pYQ07XCXTWXUBN4q2TCMG-sJ9gmXfRBhfk=s128",
      "image_original_url": "https://ipfs.infura.io/ipfs/QmcpzcLSFqwZVWa33xxhPWQQKZ7Nvr8emi89ketj2eBgKw/asset.jpeg",
      "animation_url": null,
      "animation_original_url": null,
      "name": "Wild Hearts 2021 Sabet",
      "description": "I have a wild heart. It yearns to love. It expands to heal. And it desires to love.",
      "external_link": "https://knownorigin.io/token/611423",
      "asset_contract": {
        "address": "0xfbeef911dc5821886e1dda71586d90ed28174b7d",
        "asset_contract_type": "non-fungible",
        "created_date": "2018-09-26T14:13:07.725021",
        "name": "Known Origin",
        "nft_version": "3.0",
        "opensea_version": null,
        "owner": 82615,
        "schema_name": "ERC721",
        "symbol": "KODA",
        "total_supply": null,
        "description": "Discover rare digital art and collect NFTs. \r\n\r\nSince Apr. 2018.",
        "external_link": "https://knownorigin.io",
        "image_url": "https://lh3.googleusercontent.com/53L422-5QSOKOaWTu3-EWZkymYoyFo6L60AnxPXqz4rNgX1-E162tIljSyVOa3hyVACvJNGdih4lFummnHPx-1Fa=s60",
        "default_to_fiat": false,
        "dev_buyer_fee_basis_points": 0,
        "dev_seller_fee_basis_points": 1250,
        "only_proxied_transfers": false,
        "opensea_buyer_fee_basis_points": 0,
        "opensea_seller_fee_basis_points": 250,
        "buyer_fee_basis_points": 0,
        "seller_fee_basis_points": 1500,
        "payout_address": "0x11b0d9afd49dc36d86dea579d0d11771a4f2f54b"
      },
      "permalink": "https://opensea.io/assets/0xfbeef911dc5821886e1dda71586d90ed28174b7d/611423",
      "collection": {
        "banner_image_url": "https://lh3.googleusercontent.com/iL9v2veoF3jjRFI8w9GGVNd0cApJ-ydat-Qr9uVbaf4u0YQTLNBngUUMUstsRFWoVXwOXx1B0-QM-US6--pRhEYnp1eulaR8cNbEew=s2500",
        "chat_url": null,
        "created_date": "2019-04-26T22:13:10.262099",
        "default_to_fiat": false,
        "description": "Discover rare digital art and collect NFTs. \r\n\r\nSince Apr. 2018.",
        "dev_buyer_fee_basis_points": "0",
        "dev_seller_fee_basis_points": "1250",
        "discord_url": "https://discord.gg/yqgnNyZ",
        "display_data": {
          "card_display_style": "cover"
        },
        "external_url": "https://knownorigin.io",
        "featured": false,
        "featured_image_url": "https://lh3.googleusercontent.com/C8EnLXgLFLqA_o-7FdUzUGb2U0Q_N-QXjvqwv648G0RJ8smrA6UpYzcvIl6q4a2YaR-r9sbukD2f2IXPgPInywITco_eQq3d5B_smw=s300",
        "hidden": false,
        "safelist_request_status": "verified",
        "image_url": "https://lh3.googleusercontent.com/53L422-5QSOKOaWTu3-EWZkymYoyFo6L60AnxPXqz4rNgX1-E162tIljSyVOa3hyVACvJNGdih4lFummnHPx-1Fa=s60",
        "is_subject_to_whitelist": false,
        "large_image_url": "https://lh3.googleusercontent.com/C8EnLXgLFLqA_o-7FdUzUGb2U0Q_N-QXjvqwv648G0RJ8smrA6UpYzcvIl6q4a2YaR-r9sbukD2f2IXPgPInywITco_eQq3d5B_smw=s300",
        "medium_username": "knownorigin",
        "name": "KnownOrigin",
        "only_proxied_transfers": false,
        "opensea_buyer_fee_basis_points": "0",
        "opensea_seller_fee_basis_points": "250",
        "payout_address": "0x11b0d9afd49dc36d86dea579d0d11771a4f2f54b",
        "require_email": false,
        "short_description": null,
        "slug": "known-origin",
        "telegram_url": "https://t.me/knownorigin_io",
        "twitter_username": "knownorigin_io",
        "instagram_username": "knownorigin.io",
        "wiki_url": null
      },
      "decimals": 0,
      "token_metadata": "https://ipfs.infura.io/ipfs/QmZsthqNha6NjVF9kd8P9JA67XeGtcMF826BpQtLV6ST7y",
      "owner": {
        "user": {
          "username": "Jimsvault"
        },
        "profile_img_url": "https://storage.googleapis.com/opensea-static/opensea-profile/6.png",
        "address": "0x010acffec14a6413b3efaab0023996559edc4878",
        "config": ""
      }
    },
    "asset_bundle": null,
    "auction_type": null,
    "bid_amount": null,
    "collection_slug": "known-origin",
    "contract_address": "0x7be8076f4ea4a4ad08075c2508e481d6c946d12b",
    "created_date": "2021-12-29T17:35:22.331246",
    "custom_event_name": null,
    "dev_fee_payment_event": {
      "asset": null,
      "asset_bundle": null,
      "event_type": "payout",
      "event_timestamp": "2022-01-04T14:17:17",
      "auction_type": null,
      "total_price": null,
      "payment_token": {
        "id": 1,
        "symbol": "ETH",
        "address": "0x0000000000000000000000000000000000000000",
        "image_url": "https://storage.opensea.io/files/6f8e2979d428180222796ff4a33ab929.svg",
        "name": "Ether",
        "decimals": 18,
        "eth_price": "1.000000000000000",
        "usd_price": "3139.480000000000018000"
      },
      "transaction": {
        "block_hash": "0xce14ca0c1a36c0f55e79e8ace249bd98ca5ec4f05e7266cc9373e4ddd34ee13b",
        "block_number": "13939459",
        "from_account": null,
        "id": 240226195,
        "timestamp": null,
        "to_account": null,
        "transaction_hash": "0x39e4c11a02bc39cbb440acd1d47a76b63af630fc78647a68ca07105eb777cb2f",
        "transaction_index": "103"
      },
      "created_date": "2022-01-04T14:17:41.083176",
      "quantity": null
    },
    "dev_seller_fee_basis_points": 1250,
    "duration": null,
    "ending_price": null,
    "event_type": "successful",
    "from_account": null,
    "id": 2661732702,
    "is_private": true,
    "owner_account": null,
    "payment_token": {
      "id": 1,
      "symbol": "ETH",
      "address": "0x0000000000000000000000000000000000000000",
      "image_url": "https://storage.opensea.io/files/6f8e2979d428180222796ff4a33ab929.svg",
      "name": "Ether",
      "decimals": 18,
      "eth_price": "1.000000000000000",
      "usd_price": "3139.480000000000018000"
    },
    "quantity": "1",
    "seller": {
      "user": {
        "username": "Jimbol"
      },
      "profile_img_url": "https://storage.googleapis.com/opensea-static/opensea-profile/32.png",
      "address": "0x9499054d02a725316d61fa896c29d58550ee4a5b",
      "config": ""
    },
    "starting_price": null,
    "to_account": null,
    "total_price": "100000000000000000",
    "transaction": {
      "block_hash": "0x78374e6d6d5440c8d0170a579b1ec23b175a9286f6cb23999caefc8273087755",
      "block_number": "13901616",
      "from_account": {
        "user": {
          "username": "carys"
        },
        "profile_img_url": "https://storage.googleapis.com/opensea-static/opensea-profile/31.png",
        "address": "0xd711e8975f248216dba4730c06fc86b9aa765f92",
        "config": ""
      },
      "id": 235346956,
      "timestamp": "2021-12-29T17:34:56",
      "to_account": {
        "user": {
          "username": "OpenSea-Orders"
        },
        "profile_img_url": "https://storage.googleapis.com/opensea-static/opensea-profile/22.png",
        "address": "0x7be8076f4ea4a4ad08075c2508e481d6c946d12b",
        "config": "verified"
      },
      "transaction_hash": "0x8a42f5781c44ed50b124f61e4c54001543411cd256e9f3c73e0bcb60f8095da5",
      "transaction_index": "211"
    },
    "winner_account": {
      "user": {
        "username": "carys"
      },
      "profile_img_url": "https://storage.googleapis.com/opensea-static/opensea-profile/31.png",
      "address": "0xd711e8975f248216dba4730c06fc86b9aa765f92",
      "config": ""
    },
    "listing_time": "2021-12-27T23:16:59"
  },
  {
    "approved_account": null,
    "asset": {
      "id": 194852431,
      "token_id": "5972000",
      "num_sales": 1,
      "background_color": null,
      "image_url": "https://lh3.googleusercontent.com/FDMRFFTnoHSm12aVw5SX46gCLlJClc6bLvyPAr0ZhuWH31oGo29PJiitHEgW0pjdQZKYQhcXyG3_gTbtoik605J6Bk_fEPbTEcHZ",
      "image_preview_url": "https://lh3.googleusercontent.com/FDMRFFTnoHSm12aVw5SX46gCLlJClc6bLvyPAr0ZhuWH31oGo29PJiitHEgW0pjdQZKYQhcXyG3_gTbtoik605J6Bk_fEPbTEcHZ=s250",
      "image_thumbnail_url": "https://lh3.googleusercontent.com/FDMRFFTnoHSm12aVw5SX46gCLlJClc6bLvyPAr0ZhuWH31oGo29PJiitHEgW0pjdQZKYQhcXyG3_gTbtoik605J6Bk_fEPbTEcHZ=s128",
      "image_original_url": "https://ipfs.io/ipfs/QmfBzUDAjRoS924e76y2n8ZvyjtTGxy8W9nEr1eiNu54AN/asset.gif",
      "animation_url": "https://storage.opensea.io/files/6ad001e7c284851f58b6deddc4db98cb.mp4",
      "animation_original_url": "https://ipfs.io/ipfs/QmbuqKc9jSSJomRwE3EhJKJP4vsg4A6o7QMvr4SFdKpqPU/asset.mp4",
      "name": "Computer Guy's Dog",
      "description": "Our busy world and its bumpy roads. A reality probably no less stressful than a million years ago :), fighting for resources and running around in a perfect ball-shaped Earth:)\n\nmp4  26sec loop \n\nProduction time: 3 days, Tablet, Photoshop",
      "external_link": "https://knownorigin.io/0x297bcc81284d97494a4fc5d9c9f8cbb9a884a5a0",
      "asset_contract": {
        "address": "0xabb3738f04dc2ec20f4ae4462c3d069d02ae045b",
        "asset_contract_type": "non-fungible",
        "created_date": "2021-08-25T10:45:22.442150",
        "name": "KnownOriginDigitalAsset",
        "nft_version": "3.0",
        "opensea_version": null,
        "owner": null,
        "schema_name": "ERC721",
        "symbol": "KODA",
        "total_supply": null,
        "description": "Discover rare digital art and collect NFTs. \r\n\r\nSince Apr. 2018.",
        "external_link": "https://knownorigin.io",
        "image_url": "https://lh3.googleusercontent.com/53L422-5QSOKOaWTu3-EWZkymYoyFo6L60AnxPXqz4rNgX1-E162tIljSyVOa3hyVACvJNGdih4lFummnHPx-1Fa=s60",
        "default_to_fiat": false,
        "dev_buyer_fee_basis_points": 0,
        "dev_seller_fee_basis_points": 1250,
        "only_proxied_transfers": false,
        "opensea_buyer_fee_basis_points": 0,
        "opensea_seller_fee_basis_points": 250,
        "buyer_fee_basis_points": 0,
        "seller_fee_basis_points": 1500,
        "payout_address": "0x11b0d9afd49dc36d86dea579d0d11771a4f2f54b"
      },
      "permalink": "https://opensea.io/assets/0xabb3738f04dc2ec20f4ae4462c3d069d02ae045b/5972000",
      "collection": {
        "banner_image_url": "https://lh3.googleusercontent.com/iL9v2veoF3jjRFI8w9GGVNd0cApJ-ydat-Qr9uVbaf4u0YQTLNBngUUMUstsRFWoVXwOXx1B0-QM-US6--pRhEYnp1eulaR8cNbEew=s2500",
        "chat_url": null,
        "created_date": "2019-04-26T22:13:10.262099",
        "default_to_fiat": false,
        "description": "Discover rare digital art and collect NFTs. \r\n\r\nSince Apr. 2018.",
        "dev_buyer_fee_basis_points": "0",
        "dev_seller_fee_basis_points": "1250",
        "discord_url": "https://discord.gg/yqgnNyZ",
        "display_data": {
          "card_display_style": "cover"
        },
        "external_url": "https://knownorigin.io",
        "featured": false,
        "featured_image_url": "https://lh3.googleusercontent.com/C8EnLXgLFLqA_o-7FdUzUGb2U0Q_N-QXjvqwv648G0RJ8smrA6UpYzcvIl6q4a2YaR-r9sbukD2f2IXPgPInywITco_eQq3d5B_smw=s300",
        "hidden": false,
        "safelist_request_status": "verified",
        "image_url": "https://lh3.googleusercontent.com/53L422-5QSOKOaWTu3-EWZkymYoyFo6L60AnxPXqz4rNgX1-E162tIljSyVOa3hyVACvJNGdih4lFummnHPx-1Fa=s60",
        "is_subject_to_whitelist": false,
        "large_image_url": "https://lh3.googleusercontent.com/C8EnLXgLFLqA_o-7FdUzUGb2U0Q_N-QXjvqwv648G0RJ8smrA6UpYzcvIl6q4a2YaR-r9sbukD2f2IXPgPInywITco_eQq3d5B_smw=s300",
        "medium_username": "knownorigin",
        "name": "KnownOrigin",
        "only_proxied_transfers": false,
        "opensea_buyer_fee_basis_points": "0",
        "opensea_seller_fee_basis_points": "250",
        "payout_address": "0x11b0d9afd49dc36d86dea579d0d11771a4f2f54b",
        "require_email": false,
        "short_description": null,
        "slug": "known-origin",
        "telegram_url": "https://t.me/knownorigin_io",
        "twitter_username": "knownorigin_io",
        "instagram_username": "knownorigin.io",
        "wiki_url": null
      },
      "decimals": 0,
      "token_metadata": "https://ipfs.io/ipfs/QmbPe9nqCvS8GDbjrNKPz9a1LFkcTDgHqsAtJBdMqsCAVk",
      "owner": {
        "user": {
          "username": "C34"
        },
        "profile_img_url": "https://storage.googleapis.com/opensea-static/opensea-profile/21.png",
        "address": "0x694e64d4ad77e0c234b7b1c55ac40302ad86ce3f",
        "config": ""
      }
    },
    "asset_bundle": null,
    "auction_type": null,
    "bid_amount": null,
    "collection_slug": "known-origin",
    "contract_address": "0x7be8076f4ea4a4ad08075c2508e481d6c946d12b",
    "created_date": "2022-01-08T13:48:35.084796",
    "custom_event_name": null,
    "dev_fee_payment_event": {
      "asset": null,
      "asset_bundle": null,
      "event_type": "payout",
      "event_timestamp": "2022-01-11T03:20:34",
      "auction_type": null,
      "total_price": null,
      "payment_token": {
        "id": 1,
        "symbol": "ETH",
        "address": "0x0000000000000000000000000000000000000000",
        "image_url": "https://storage.opensea.io/files/6f8e2979d428180222796ff4a33ab929.svg",
        "name": "Ether",
        "decimals": 18,
        "eth_price": "1.000000000000000",
        "usd_price": "3139.480000000000018000"
      },
      "transaction": {
        "block_hash": "0xeb0523d4ea16092eb41e7f5bd16b79141de9fdb7cebf7dfc70501cedcefb4da2",
        "block_number": "13981749",
        "from_account": null,
        "id": 244933879,
        "timestamp": null,
        "to_account": null,
        "transaction_hash": "0xc861d11e31baff5a91433a6936218e7b091dd8b47336a59c72e990d3be6540f1",
        "transaction_index": "74"
      },
      "created_date": "2022-01-11T03:21:21.350523",
      "quantity": null
    },
    "dev_seller_fee_basis_points": 1250,
    "duration": null,
    "ending_price": null,
    "event_type": "successful",
    "from_account": null,
    "id": 2801385268,
    "is_private": true,
    "owner_account": null,
    "payment_token": {
      "id": 1,
      "symbol": "ETH",
      "address": "0x0000000000000000000000000000000000000000",
      "image_url": "https://storage.opensea.io/files/6f8e2979d428180222796ff4a33ab929.svg",
      "name": "Ether",
      "decimals": 18,
      "eth_price": "1.000000000000000",
      "usd_price": "3139.480000000000018000"
    },
    "quantity": "1",
    "seller": {
      "user": {
        "username": "DUNATA"
      },
      "profile_img_url": "https://storage.googleapis.com/opensea-static/opensea-profile/15.png",
      "address": "0x297bcc81284d97494a4fc5d9c9f8cbb9a884a5a0",
      "config": ""
    },
    "starting_price": null,
    "to_account": null,
    "total_price": "0",
    "transaction": {
      "block_hash": "0x76a2b70068f8a6ab6d56bbc759188209457f8b00894fd733d878888865584933",
      "block_number": "13965107",
      "from_account": {
        "user": {
          "username": "C34"
        },
        "profile_img_url": "https://storage.googleapis.com/opensea-static/opensea-profile/21.png",
        "address": "0x694e64d4ad77e0c234b7b1c55ac40302ad86ce3f",
        "config": ""
      },
      "id": 242797372,
      "timestamp": "2022-01-08T13:48:07",
      "to_account": {
        "user": {
          "username": "OpenSea-Orders"
        },
        "profile_img_url": "https://storage.googleapis.com/opensea-static/opensea-profile/22.png",
        "address": "0x7be8076f4ea4a4ad08075c2508e481d6c946d12b",
        "config": "verified"
      },
      "transaction_hash": "0x1467c7c03292833d8fa8785072d17a1d2d94a871f30e3b255a4ee7e82df48ab1",
      "transaction_index": "105"
    },
    "winner_account": {
      "user": {
        "username": "C34"
      },
      "profile_img_url": "https://storage.googleapis.com/opensea-static/opensea-profile/21.png",
      "address": "0x694e64d4ad77e0c234b7b1c55ac40302ad86ce3f",
      "config": ""
    },
    "listing_time": "2022-01-08T13:41:04"
  }
]